slicerfiducials/__init__.py
slicerfiducials/cli.py
slicerfiducials/slicerfiducials.py
slicerfiducials/enumerations/__init__.py
slicerfiducials/enumerations/format.py
slicerfiducials/enumerations/space.py
slicerfiducials-0.1.6.dist-info/AUTHORS.rst
slicerfiducials-0.1.6.dist-info/LICENSE
slicerfiducials-0.1.6.dist-info/METADATA
slicerfiducials-0.1.6.dist-info/WHEEL
slicerfiducials-0.1.6.dist-info/entry_points.txt
slicerfiducials-0.1.6.dist-info/top_level.txt
slicerfiducials-0.1.6.dist-info/RECORD
