Metadata-Version: 2.1
Name: slicerfiducials
Version: 0.1.6
Summary: A project to manage code for manipulating slicer ficucials
Home-page: https://github.com/abpwrs/slicerfiducials
Author: Alexander Powers
Author-email: alexander-powers@uiowa.edu
License: GNU General Public License v3
Keywords: slicerfiducials
Platform: UNKNOWN
Classifier: Development Status :: 2 - Pre-Alpha
Classifier: Intended Audience :: Developers
Classifier: License :: OSI Approved :: GNU General Public License v3 (GPLv3)
Classifier: Natural Language :: English
Classifier: Programming Language :: Python :: 3
Classifier: Programming Language :: Python :: 3.5
Classifier: Programming Language :: Python :: 3.6
Classifier: Programming Language :: Python :: 3.7
Classifier: Programming Language :: Python :: 3.8
Requires-Python: >=3.5
Requires-Dist: itk
Requires-Dist: numpy
Requires-Dist: pandas
Requires-Dist: simpleitk
